castanet/__init__.py
castanet/counter.py
castanet/generate_trees.py
castanet/main.py
castanet-1.3.0.dist-info/entry_points.txt
castanet-1.3.0.dist-info/WHEEL
castanet-1.3.0.dist-info/METADATA
castanet-1.3.0.dist-info/RECORD
