Metadata-Version: 2.1
Name: castanet
Version: 1.3.0
Summary: Program to identify different syntax markers in Python programs
Home-page: https://github.com/cmpsc-481-s22-m1/CASTanet
License: AC
Author: Thomas Antle, Caden Hinckley, Maddy Kapfhammer, Bailey Matrascia, Nolan Thompson
Requires-Python: >=3.7,<4.0
Classifier: License :: Other/Proprietary License
Classifier: Programming Language :: Python :: 3
Classifier: Programming Language :: Python :: 3.7
Classifier: Programming Language :: Python :: 3.8
Classifier: Programming Language :: Python :: 3.9
Requires-Dist: libcst (>=0.4.0,<0.5.0)
Requires-Dist: prettyprint (>=0.1.5,<0.2.0)
Requires-Dist: typer[all] (>=0.4.0,<0.5.0)
Project-URL: Repository, https://github.com/cmpsc-481-s22-m1/CASTanet
